nibiru_proto/__init__.py
nibiru_proto/amino/amino_pb2.py
nibiru_proto/amino/amino_pb2.pyi
nibiru_proto/amino/amino_pb2_grpc.py
nibiru_proto/cosmos/app/runtime/v1alpha1/module_pb2.py
nibiru_proto/cosmos/app/runtime/v1alpha1/module_pb2.pyi
nibiru_proto/cosmos/app/runtime/v1alpha1/module_pb2_grpc.py
nibiru_proto/cosmos/app/v1alpha1/config_pb2.py
nibiru_proto/cosmos/app/v1alpha1/config_pb2.pyi
nibiru_proto/cosmos/app/v1alpha1/config_pb2_grpc.py
nibiru_proto/cosmos/app/v1alpha1/module_pb2.py
nibiru_proto/cosmos/app/v1alpha1/module_pb2.pyi
nibiru_proto/cosmos/app/v1alpha1/module_pb2_grpc.py
nibiru_proto/cosmos/app/v1alpha1/query_pb2.py
nibiru_proto/cosmos/app/v1alpha1/query_pb2.pyi
nibiru_proto/cosmos/app/v1alpha1/query_pb2_grpc.py
nibiru_proto/cosmos/auth/module/v1/module_pb2.py
nibiru_proto/cosmos/auth/module/v1/module_pb2.pyi
nibiru_proto/cosmos/auth/module/v1/module_pb2_grpc.py
nibiru_proto/cosmos/auth/v1beta1/auth_pb2.py
nibiru_proto/cosmos/auth/v1beta1/auth_pb2.pyi
nibiru_proto/cosmos/auth/v1beta1/auth_pb2_grpc.py
nibiru_proto/cosmos/auth/v1beta1/genesis_pb2.py
nibiru_proto/cosmos/auth/v1beta1/genesis_pb2.pyi
nibiru_proto/cosmos/auth/v1beta1/genesis_pb2_grpc.py
nibiru_proto/cosmos/auth/v1beta1/query_pb2.py
nibiru_proto/cosmos/auth/v1beta1/query_pb2.pyi
nibiru_proto/cosmos/auth/v1beta1/query_pb2_grpc.py
nibiru_proto/cosmos/auth/v1beta1/tx_pb2.py
nibiru_proto/cosmos/auth/v1beta1/tx_pb2.pyi
nibiru_proto/cosmos/auth/v1beta1/tx_pb2_grpc.py
nibiru_proto/cosmos/authz/module/v1/module_pb2.py
nibiru_proto/cosmos/authz/module/v1/module_pb2.pyi
nibiru_proto/cosmos/authz/module/v1/module_pb2_grpc.py
nibiru_proto/cosmos/authz/v1beta1/authz_pb2.py
nibiru_proto/cosmos/authz/v1beta1/authz_pb2.pyi
nibiru_proto/cosmos/authz/v1beta1/authz_pb2_grpc.py
nibiru_proto/cosmos/authz/v1beta1/event_pb2.py
nibiru_proto/cosmos/authz/v1beta1/event_pb2.pyi
nibiru_proto/cosmos/authz/v1beta1/event_pb2_grpc.py
nibiru_proto/cosmos/authz/v1beta1/genesis_pb2.py
nibiru_proto-0.21.9.dist-info/LICENSE
nibiru_proto-0.21.9.dist-info/WHEEL
nibiru_proto-0.21.9.dist-info/METADATA
nibiru_proto-0.21.9.dist-info/RECORD
