Metadata-Version: 2.1
Name: nibiru-proto
Version: 0.21.9
Summary: Nibiru Chain Python SDK
License: MIT
Author: Nibiru Chain
Author-email: dev@nibiru.fi
Requires-Python: >=3.8,<4.0
Classifier: License :: OSI Approved :: MIT License
Classifier: Programming Language :: Python :: 3
Classifier: Programming Language :: Python :: 3.8
Classifier: Programming Language :: Python :: 3.9
Classifier: Programming Language :: Python :: 3.10
Classifier: Programming Language :: Python :: 3.11
Requires-Dist: asyncio (>=3.4.3,<4.0.0)
Requires-Dist: bech32 (>=1.2.0,<2.0.0)
Requires-Dist: grpcio (>=1.51.1,<2.0.0)
Requires-Dist: grpcio-tools (>=1.51.1,<2.0.0)
Requires-Dist: mypy-protobuf (>=3.4.0,<4.0.0)
Requires-Dist: protobuf (>=4.21.12,<5.0.0)
Requires-Dist: types-protobuf (>=4.21.0.2,<5.0.0.0)
